{
  "type": "exams",
  "sub": "qudrat_cognitive",
  "game_mode": "cell",
  "easy": {
    "أ": [
      {
        "q": "من الاستدلال، الانتقال من العام للخاص؟",
        "a": "استنباط",
        "o": [
          "استنباط",
          "استقراء",
          "ملاحظة",
          "تجريب"
        ],
        "h": "يبدأ بالألف"
      }
    ],
    "ب": [
      {
        "q": "معلومات أولية يتم جمعها؟",
        "a": "بيانات",
        "o": [
          "بيانات",
          "قرارات",
          "أحكام",
          "آراء"
        ],
        "h": "قبل المعالجة"
      }
    ],
    "ت": [
      {
        "q": "علاقة عكسية بين كلمتين؟",
        "a": "تضاد",
        "o": [
          "تضاد",
          "ترادف",
          "تشابه",
          "تطابق"
        ],
        "h": "عكس المعنى"
      }
    ],
    "ث": [
      {
        "q": "الشيء الذي لا يتغير؟",
        "a": "ثابت",
        "o": [
          "ثابت",
          "متغير",
          "متحرك",
          "متبدل"
        ],
        "h": "عكس المتغير"
      }
    ],
    "ج": [
      {
        "q": "أداة لتنظيم البيانات في صفوف وأعمدة؟",
        "a": "جدول",
        "o": [
          "جدول",
          "رسم",
          "نص",
          "صورة"
        ],
        "h": "يستخدم للمقارنة"
      }
    ],
    "ح": [
      {
        "q": "عملية رياضية للوصول لنتيجة رقمية؟",
        "a": "حساب",
        "o": [
          "حساب",
          "كتابة",
          "قراءة",
          "رسم"
        ],
        "h": "جمع وطرح..."
      }
    ],
    "خ": [
      {
        "q": "تمثيل مرسوم لمنطقة أو مكان؟",
        "a": "خريطة",
        "o": [
          "خريطة",
          "صورة",
          "نص",
          "جدول"
        ],
        "h": "قدرة مكانية"
      }
    ],
    "د": [
      {
        "q": "ما يثبت صحة الفرضية؟",
        "a": "دليل",
        "o": [
          "دليل",
          "شك",
          "وهم",
          "ظن"
        ],
        "h": "برهان"
      }
    ],
    "ذ": [
      {
        "q": "قدرة عقلية عامة؟",
        "a": "ذكاء",
        "o": [
          "ذكاء",
          "طول",
          "وزن",
          "سرعة"
        ],
        "h": "يبدأ بحرف الذال"
      }
    ],
    "ر": [
      {
        "q": "أشكال بيانية توضح البيانات؟",
        "a": "رسوم",
        "o": [
          "رسوم",
          "نصوص",
          "أرقام",
          "حروف"
        ],
        "h": "رسم بياني"
      }
    ],
    "ز": [
      {
        "q": "البعد الرابع، يقاس بالساعة؟",
        "a": "زمن",
        "o": [
          "زمن",
          "مكان",
          "مسافة",
          "سرعة"
        ],
        "h": "وقت"
      }
    ],
    "س": [
      {
        "q": "مجموعة أرقام تتبع نمطاً معيناً؟",
        "a": "سلسلة",
        "o": [
          "سلسلة",
          "فوضى",
          "عشوائية",
          "تشتت"
        ],
        "h": "متتابعة"
      }
    ],
    "ش": [
      {
        "q": "صورة خارجية للشيء (مثل المربع والدائرة)؟",
        "a": "شكل",
        "o": [
          "شكل",
          "لون",
          "طعم",
          "رائحة"
        ],
        "h": "قدرة مكانية"
      }
    ],
    "ص": [
      {
        "q": "مجسم ثلاثي الأبعاد له 6 أوجه؟",
        "a": "صندوق",
        "o": [
          "صندوق",
          "ورقة",
          "خط",
          "نقطة"
        ],
        "h": "يستخدم في التصور المكاني"
      }
    ],
    "ض": [
      {
        "q": "ضرب العدد في 2؟",
        "a": "ضعف",
        "o": [
          "ضعف",
          "نصف",
          "ربع",
          "ثلث"
        ],
        "h": "مثلي الشيء"
      }
    ],
    "ط": [
      {
        "q": "عملية عكس الجمع؟",
        "a": "طرح",
        "o": [
          "طرح",
          "ضرب",
          "قسمة",
          "أس"
        ],
        "h": "ناقص"
      }
    ],
    "ظ": [
      {
        "q": "الحالة المحيطة بالحدث؟",
        "a": "ظرف",
        "o": [
          "ظرف",
          "جدار",
          "أرض",
          "سماء"
        ],
        "h": "ظرف زمان أو مكان"
      }
    ],
    "ع": [
      {
        "q": "رابط بين شيئين أو متغيرين؟",
        "a": "علاقة",
        "o": [
          "علاقة",
          "انفصال",
          "تباعد",
          "تنافر"
        ],
        "h": "طردية أو عكسية"
      }
    ],
    "غ": [
      {
        "q": "كلمة تفيد النفي أو الاختلاف؟",
        "a": "غير",
        "o": [
          "غير",
          "نعم",
          "تأكيد",
          "إثبات"
        ],
        "h": "الغير"
      }
    ],
    "ف": [
      {
        "q": "مجموعة تشترك في خصائص معينة؟",
        "a": "فئة",
        "o": [
          "فئة",
          "فرد",
          "جزء",
          "عنصر"
        ],
        "h": "تصنيف"
      }
    ],
    "ق": [
      {
        "q": "إمكانية أداء عمل ما؟",
        "a": "قدرة",
        "o": [
          "قدرة",
          "عجز",
          "كسل",
          "ضعف"
        ],
        "h": "اسم الاختبار"
      }
    ],
    "ك": [
      {
        "q": "نوع الاستدلال المتعلق بالأرقام؟",
        "a": "كمي",
        "o": [
          "كمي",
          "لفظي",
          "مكاني",
          "منطقي"
        ],
        "h": "عددي"
      }
    ],
    "ل": [
      {
        "q": "نوع الاستدلال المتعلق بالكلمات؟",
        "a": "لفظي",
        "o": [
          "لفظي",
          "كمي",
          "رياضي",
          "هندسي"
        ],
        "h": "لغوي"
      }
    ],
    "م": [
      {
        "q": "مجسم هندسي جميع أضلاعه متساوية؟",
        "a": "مكعب",
        "o": [
          "مكعب",
          "مربع",
          "دائرة",
          "مثلث"
        ],
        "h": "شكل ثلاثي الأبعاد"
      }
    ]
  }
}